{"id":562,"guid":"fbf1e851-b9aa-4a30-9faf-02cdb1fc7e21","name":"Geofabrik Water","desc":"","type":"wms","epsg":3857,"license_name":"","license_url":"","copyright_text":"© 2014 Geofabrik GmbH Karlsruhe","copyright_url":"","terms_of_use_url":"","created_at":"2016-11-14T18:08:04.486371Z","updated_at":"2016-11-14T18:08:18.682409Z","source":null,"source_url":null,"url":"http://tools.geofabrik.de/osmi/view/water/wxs?VERSION=1.1.1&","params":"format=image/png&crs=EPSG:3857","layers":"riverbank_areas,water_areas,coastline,waterways_width,waterways_in_tunnels,waterways_on_bridges,waterways_drain,waterways_canal,waterways_stream,waterways_river,waterways_riverbank,waterways_other,waterrelations_drain,waterrelations_canal,waterrelations_stream,waterrelations_river,waterrelations_riverbank,waterrelations_other,waterways_without_names,waterway_nodes,rivermouths,outflows","turn_over":false,"format":null,"icon":null,"submitter":null}