{"id":655,"guid":"e66cae2e-b993-49d8-aca9-3d5e8dcee559","name":"NE Physical Land (110m)","desc":"Natural Earth Physical Land (110m)","type":"geojson","epsg":4326,"license_name":"Public Domain","license_url":"http://creativecommons.org/publicdomain/","copyright_text":"","copyright_url":"","terms_of_use_url":"","created_at":"2016-12-13T04:58:54.993944Z","updated_at":"2016-12-13T04:58:54.994001Z","source":"http://www.naturalearthdata.com/downloads/110m-physical-vectors/","source_url":"","url":"http://data.nextgis.ru/api/resource/92/geojson","icon":null,"submitter":"349a7b2a-3795-43f7-96f9-da0615ff23c3"}