{"id":666,"guid":"96b0a787-5d4a-469b-b106-8df246c5b17d","name":"Global Surface Summary of the Day","desc":"Meteorological stations used in the Global Surface Summary of the Day (GSOD) service","type":"wms","epsg":null,"license_name":"","license_url":"","copyright_text":"","copyright_url":"","terms_of_use_url":"","created_at":"2016-12-23T20:58:30.603575Z","updated_at":"2016-12-25T00:06:25.388878Z","source":"https://data.noaa.gov/dataset/global-surface-summary-of-the-day-gsod","source_url":"","url":"https://gis.ncdc.noaa.gov/arcgis/services/cdo/gsod/MapServer/WMSServer","params":"","layers":"0","turn_over":false,"format":"image/png","icon":null,"submitter":"abeff207-a0c0-427a-a771-24c153697f2d"}